mlflow_gcp_iap_plugin/__init__.py
mlflow_gcp_iap_plugin/request_header_provider.py
mlflow_gcp_iap_plugin-0.0.2.dist-info/LICENSE.txt
mlflow_gcp_iap_plugin-0.0.2.dist-info/METADATA
mlflow_gcp_iap_plugin-0.0.2.dist-info/WHEEL
mlflow_gcp_iap_plugin-0.0.2.dist-info/entry_points.txt
mlflow_gcp_iap_plugin-0.0.2.dist-info/top_level.txt
mlflow_gcp_iap_plugin-0.0.2.dist-info/RECORD
