Metadata-Version: 2.1
Name: mlflow-gcp-iap-plugin
Version: 0.0.2
Summary: Test plugin for MLflow.  Allows using URI which is behind IAP by setting environment variable of 'MLFLOW_IAP_CLIENT_ID' to the client id of the IAP.
Home-page: https://bitbucket.org/abridge-ai/mlflow-gcp-iap-plugin
Author: Nathan Price
Author-email: nathan@abridge.com
License: UNKNOWN
Project-URL: Bug Tracker, https://bitbucket.org/abridge-ai/mlflow-gcp-iap-plugin/issues
Platform: UNKNOWN
Classifier: Programming Language :: Python :: 3
Classifier: License :: OSI Approved :: MIT License
Classifier: Operating System :: OS Independent
Requires-Python: >=3.6
License-File: LICENSE.txt
Requires-Dist: mlflow
Requires-Dist: google-auth
Requires-Dist: google-oauth
